Workbook

Sheet liste des taches
A1: Ligne | B1: Catégorie | C1: Module | D1: Nom Page | E1: Description | F1: Type | G1: Estimation (h) | H1: Temps passé (h) | I1: Reste à faire (h) | J1: Avancement | K1: Qui | L1: Statut
A2: 1 | B2: Auth · Profil · IMC | C2: F1 — Gestion des Rôles | D2: Middleware | E2: Middleware CodeIgniter vérifiant $_SESSION['role'] avant chaque contrôleur | F2: Backend | G2: 3 | H2: 3 | I2: =G2-H2 -> 0 | J2: =IF((H2+I2)=0,0,H2/(H2+I2)) -> 1 | K2: Eddy | L2: ✅ OK
A3: 2 | B3: Auth · Profil · IMC | C3: F1 — Gestion des Rôles | D3: home.php | E3: Page d'accueil publique avec présentation et calcul IMC rapide (sans inscription) | F3: Frontend | G3: 4 | H3: 4 | I3: =G3-H3 -> 0 | J3: =IF((H3+I3)=0,0,H3/(H3+I3)) -> 1 | K3: Eddy | L3: ✅ OK
A4: 3 | B4: Auth · Profil · IMC | C4: F1 — Gestion des Rôles | D4: regimes_preview.php | E4: Aperçu régimes pour visiteur : nom, objectif, durée, prix — sans détail aliments | F4: Frontend | G4: 3 | H4: 3 | I4: =G4-H4 -> 0 | J4: =IF((H4+I4)=0,0,H4/(H4+I4)) -> 1 | K4: Eddy | L4: ✅ OK
A5: 4 | B5: Auth · Profil · IMC | C5: F1 — Gestion des Rôles | D5: sports_preview.php | E5: Aperçu activités sportives pour visiteur : nom, niveau, calories — sans programme | F5: Frontend | G5: 2 | H5: 2 | I5: =G5-H5 -> 0 | J5: =IF((H5+I5)=0,0,H5/(H5+I5)) -> 1 | K5: Eddy | L5: ✅ OK
A6: 5 | B6: Auth · Profil · IMC | C6: F1 — Gestion des Rôles | D6: AuthController.php | E6: Redirection automatique après login selon rôle (/dashboard ou /admin) | F6: Backend | G6: 2 | H6: 2 | I6: =G6-H6 -> 0 | J6: =IF((H6+I6)=0,0,H6/(H6+I6)) -> 1 | K6: Eddy | L6: ✅ OK
A7: 6 | B7: Auth · Profil · IMC | C7: F2 — Inscription | D7: register_step1.php | E7: Formulaire étape 1 : nom, email, genre, âge, mot de passe | F7: Frontend | G7: 3 | H7: 3 | I7: =G7-H7 -> 0 | J7: =IF((H7+I7)=0,0,H7/(H7+I7)) -> 1 | K7: Eddy | L7: ✅ OK
A8: 7 | B8: Auth · Profil · IMC | C8: F2 — Inscription | D8: register_step1.php | E8: Validation AJAX email unique : POST /user/check_email → JSON {disponible} | F8: Backend | G8: 2 | H8: 2 | I8: =G8-H8 -> 0 | J8: =IF((H8+I8)=0,0,H8/(H8+I8)) -> 1 | K8: Eddy | L8: ✅ OK
A9: 8 | B9: Auth · Profil · IMC | C9: F2 — Inscription | D9: register_step1.php | E9: Validation mot de passe min 8 caractères avec confirmation en live | F9: Frontend | G9: 2 | H9: 2 | I9: =G9-H9 -> 0 | J9: =IF((H9+I9)=0,0,H9/(H9+I9)) -> 1 | K9: Eddy | L9: ✅ OK
A10: 9 | B10: Auth · Profil · IMC | C10: F2 — Inscription | D10: register_step1.php | E10: Indicateur de progression visuel étape 1/2 + stockage temporaire session PHP | F10: Frontend | G10: 2 | H10: 2 | I10: =G10-H10 -> 0 | J10: =IF((H10+I10)=0,0,H10/(H10+I10)) -> 1 | K10: Eddy | L10: ✅ OK
A11: 10 | B11: Auth · Profil · IMC | C11: F2 — Inscription | D11: register_step2.php | E11: Formulaire étape 2 : taille (m) et poids (kg) | F11: Frontend | G11: 2 | H11: 2 | I11: =G11-H11 -> 0 | J11: =IF((H11+I11)=0,0,H11/(H11+I11)) -> 1 | K11: Eddy | L11: ✅ OK
A12: 11 | B12: Auth · Profil · IMC | C12: F2 — Inscription | D12: UserModel.php | E12: INSERT user + userBody à la validation (id_user, taille, poids, date=now) | F12: Backend | G12: 3 | H12: 3 | I12: =G12-H12 -> 0 | J12: =IF((H12+I12)=0,0,H12/(H12+I12)) -> 1 | K12: Eddy | L12: ✅ OK
A13: 12 | B13: Auth · Profil · IMC | C13: F2 — Inscription | D13: ImcHistoryModel.php | E13: Calcul IMC = poids ÷ taille² → INSERT imcHistory | F13: Backend | G13: 2 | H13: 2 | I13: =G13-H13 -> 0 | J13: =IF((H13+I13)=0,0,H13/(H13+I13)) -> 1 | K13: Eddy | L13: ✅ OK
... A70: 69 | B70: Wallet · Gold · Admin | C70: F4 — Codes prépayés | D70: admin/codes.php | E70: Désactiver un code manuellement | F70: Backend | G70: 1 | H70: 1 | I70: =G70-H70 -> 0 | J70: =IF((H70+I70)=0,0,H70/(H70+I70)) -> 1 | K70: Liantsoa | L70: ✅ OK

Sheet avancement projet
A1: 📊 Avancement Global du Projet
A2: Indicateur | B2: Valeur | C2: Formule source
A3: Estimation totale (h) | B3: =SUM('liste des taches'!G2:G70) -> 153 | C3: SUM col G
A4: Temps passé total (h) | B4: =SUM('liste des taches'!H2:H70) -> 153 | C4: SUM col H
A5: Reste à faire total (h) | B5: =SUM('liste des taches'!I2:I70) -> 0 | C5: SUM col I
A6: Avancement | B6: =B4/(B4+B5) -> 1 | C6: Temps passé / (Temps passé + Reste)
A7: Dépassement | B7: =((B4+B5)-B3)/B3 -> 0 | C7: (Passé + Reste - Estimation) / Estimation

Sheet Recap
A1: Tableau 1 — Avancement Global
A2: Indicateur | B2: Valeur
A3: Avancement | B3: ='avancement projet'!B6 -> 1
A4: Dépassement | B4: ='avancement projet'!B7 -> 0
A6: Tableau 2 — Récap par Responsable
A7: Qui | B7: Somme Estimation (h) | C7: Somme Temps passé (h) | D7: Avancement
A8: Eddy | B8: =SUMIF('liste des taches'!K2:K70,A8,'liste des taches'!G2:G70) -> 52 | C8: =SUMIF('liste des taches'!K2:K70,A8,'liste des taches'!H2:H70) -> 52 | D8: =IF(C8=0,0,C8/(C8+SUMIF('liste des taches'!K2:K70,A8,'liste des taches'!I2:I70))) -> 1
A9: Tsinjo | B9: =SUMIF('liste des taches'!K2:K70,A9,'liste des taches'!G2:G70) -> 45 | C9: =SUMIF('liste des taches'!K2:K70,A9,'liste des taches'!H2:H70) -> 45 | D9: =IF(C9=0,0,C9/(C9+SUMIF('liste des taches'!K2:K70,A9,'liste des taches'!I2:I70))) -> 1
A10: Liantsoa | B10: =SUMIF('liste des taches'!K2:K70,A10,'liste des taches'!G2:G70) -> 56 | C10: =SUMIF('liste des taches'!K2:K70,A10,'liste des taches'!H2:H70) -> 56 | D10: =IF(C10=0,0,C10/(C10+SUMIF('liste des taches'!K2:K70,A10,'liste des taches'!I2:I70))) -> 1
A11: TOTAL | B11: =SUM(B8:B10) -> 153 | C11: =SUM(C8:C10) -> 153 | D11: =IF(D8+D9+D10=0,0,(D8+D9+D10)/3) -> 1
